[
  {
    "title": "Bronzová vež",
    "url": "https://www.kosmas.cz/knihy/568509/bronzova-vez/",
    "description": "Bronzová vež - Petr Jaroněk",
    "authors": [
      "Petr Jaroněk"
    ],
    "date": "2026-05-07T07:14:20.045126+00:00"
  },
  {
    "title": "Moucha, Myš a lži",
    "url": "https://www.kosmas.cz/knihy/568510/moucha-mys-a-lzi/",
    "description": "Moucha, Myš a lži - Jana Pavloušková",
    "authors": [
      "Jana Pavloušková"
    ],
    "date": "2026-05-07T07:14:19.045126+00:00"
  },
  {
    "title": "Podpalubí",
    "url": "https://www.kosmas.cz/knihy/568534/podpalubi/",
    "description": "Podpalubí - Oliver Jasanský",
    "authors": [
      "Oliver Jasanský"
    ],
    "date": "2026-05-07T07:14:18.045126+00:00"
  },
  {
    "title": "Sad kostí",
    "url": "https://www.kosmas.cz/knihy/568535/sad-kosti/",
    "description": "Sad kostí - Martin Müller",
    "authors": [
      "Martin Müller"
    ],
    "date": "2026-05-07T07:14:17.045126+00:00"
  },
  {
    "title": "Měsíc mého života",
    "url": "https://www.kosmas.cz/knihy/568556/mesic-meho-zivota/",
    "description": "Měsíc mého života - Ondřej Neff",
    "authors": [
      "Ondřej Neff"
    ],
    "date": "2026-05-07T07:14:16.045126+00:00"
  },
  {
    "title": "Důkazní nouze",
    "url": "https://www.kosmas.cz/knihy/568607/dukazni-nouze/",
    "description": "Důkazní nouze - Ladislav Beran",
    "authors": [
      "Ladislav Beran"
    ],
    "date": "2026-05-07T07:14:15.045126+00:00"
  },
  {
    "title": "Květnová nevěsta",
    "url": "https://www.kosmas.cz/knihy/568608/kvetnova-nevesta/",
    "description": "Květnová nevěsta - Veronika Černucká",
    "authors": [
      "Veronika Černucká"
    ],
    "date": "2026-05-07T07:14:14.045126+00:00"
  },
  {
    "title": "Malá noční vražda",
    "url": "https://www.kosmas.cz/knihy/568609/mala-nocni-vrazda/",
    "description": "Malá noční vražda - Matthew Costello, Richards Neil",
    "authors": [
      "Matthew Costello",
      "Richards Neil"
    ],
    "date": "2026-05-07T07:14:13.045126+00:00"
  },
  {
    "title": "Válečný pilot",
    "url": "https://www.kosmas.cz/knihy/568619/valecny-pilot/",
    "description": "Válečný pilot - Antoine de Saint-Exupéry",
    "authors": [
      "Antoine de Saint-Exupéry"
    ],
    "date": "2026-05-07T07:14:12.045126+00:00"
  },
  {
    "title": "Slova tak sladká a smrtící",
    "url": "https://www.kosmas.cz/knihy/568677/slova-tak-sladka-a-smrtici/",
    "description": "Slova tak sladká a smrtící - Sophia St. Germain",
    "authors": [
      "Sophia St. Germain"
    ],
    "date": "2026-05-07T07:14:11.045126+00:00"
  },
  {
    "title": "Pod palbou hloubkařů – DODATKY",
    "url": "https://www.kosmas.cz/knihy/550696/pod-palbou-hloubkaru-dodatky/",
    "description": "Pod palbou hloubkařů – DODATKY - Filip Vojtášek",
    "authors": [
      "Filip Vojtášek"
    ],
    "date": "2026-05-07T07:14:10.045126+00:00"
  },
  {
    "title": "Osvícení",
    "url": "https://www.kosmas.cz/knihy/549595/osviceni/",
    "description": "Osvícení - Sarah Perryová",
    "authors": [
      "Sarah Perryová"
    ],
    "date": "2026-05-07T07:14:09.045126+00:00"
  },
  {
    "title": "Kovbojové na moři",
    "url": "https://www.kosmas.cz/knihy/549621/kovbojove-na-mori/",
    "description": "Kovbojové na moři - Petr Kos",
    "authors": [
      "Petr Kos"
    ],
    "date": "2026-05-07T07:14:08.045126+00:00"
  },
  {
    "title": "Sladké Česko",
    "url": "https://www.kosmas.cz/knihy/568242/sladke-cesko/",
    "description": "Sladké Česko - Patrik Rozehnal",
    "authors": [
      "Patrik Rozehnal"
    ],
    "date": "2026-05-07T07:14:06.045126+00:00"
  },
  {
    "title": "Nesmíš mi sem s myšmi",
    "url": "https://www.kosmas.cz/knihy/568244/nesmis-mi-sem-s-mysmi/",
    "description": "Nesmíš mi sem s myšmi - Blanka Budínová",
    "authors": [
      "Blanka Budínová"
    ],
    "date": "2026-05-07T07:14:05.045126+00:00"
  },
  {
    "title": "Anesteziologie, resuscitace a intenzivní medicína pro studenty a absolventy lékařských fakult. Anest",
    "url": "https://www.kosmas.cz/knihy/568380/anesteziologie-resuscitace-a-intenzivni-medicina-pro-studenty-a---anest/",
    "description": "Anesteziologie, resuscitace a intenzivní medicína pro studenty a absolventy lékařských fakult. Anest - Jan Bureš, Miroslav Durila, pedagogů: kolektiv, Stanislav Novotný",
    "authors": [
      "Jan Bureš",
      "Miroslav Durila",
      "pedagogů: kolektiv",
      "Stanislav Novotný"
    ],
    "date": "2026-05-07T07:14:04.045126+00:00"
  },
  {
    "title": "Stručný přehled oftalmologie",
    "url": "https://www.kosmas.cz/knihy/568408/strucny-prehled-oftalmologie/",
    "description": "Stručný přehled oftalmologie - Michelle Attzsová, Twishaa Shethová",
    "authors": [
      "Michelle Attzsová",
      "Twishaa Shethová"
    ],
    "date": "2026-05-07T07:14:03.045126+00:00"
  },
  {
    "title": "Dobrodružství v útulku – Splněný sen",
    "url": "https://www.kosmas.cz/knihy/568561/dobrodruzstvi-v-utulku-splneny-sen/",
    "description": "Dobrodružství v útulku – Splněný sen - Hannah Shawová",
    "authors": [
      "Hannah Shawová"
    ],
    "date": "2026-05-07T07:14:01.045126+00:00"
  },
  {
    "title": "Život v pitlane",
    "url": "https://www.kosmas.cz/knihy/568215/zivot-v-pitlane/",
    "description": "Život v pitlane - Calum Nicholas",
    "authors": [
      "Calum Nicholas"
    ],
    "date": "2026-05-06T07:09:05.083628+00:00"
  },
  {
    "title": "Cestujeme po Turecku",
    "url": "https://www.kosmas.cz/knihy/568537/cestujeme-po-turecku/",
    "description": "Cestujeme po Turecku - Lukáš Lhoťan",
    "authors": [
      "Lukáš Lhoťan"
    ],
    "date": "2026-05-06T07:09:04.083628+00:00"
  },
  {
    "title": "Tajemné stezky - Za skrytou krásou Ašska",
    "url": "https://www.kosmas.cz/knihy/567433/tajemne-stezky-za-skrytou-krasou-asska/",
    "description": "Tajemné stezky - Za skrytou krásou Ašska - Aleš Česal",
    "authors": [
      "Aleš Česal"
    ],
    "date": "2026-05-06T07:09:03.083628+00:00"
  },
  {
    "title": "JFK 043 - Lovci artefaktů",
    "url": "https://www.kosmas.cz/knihy/567545/jfk-043-lovci-artefaktu/",
    "description": "JFK 043 - Lovci artefaktů - Libor Machala",
    "authors": [
      "Libor Machala"
    ],
    "date": "2026-05-06T07:09:02.083628+00:00"
  },
  {
    "title": "Tak o co jde?",
    "url": "https://www.kosmas.cz/knihy/567558/tak-o-co-jde/",
    "description": "Tak o co jde? - Ivan Hamšík, Cyril Höschl",
    "authors": [
      "Ivan Hamšík",
      "Cyril Höschl"
    ],
    "date": "2026-05-06T07:09:01.083628+00:00"
  },
  {
    "title": "Břeclav – Pohansko XI.",
    "url": "https://www.kosmas.cz/knihy/568284/breclav-pohansko-xi/",
    "description": "Břeclav – Pohansko XI. - Adéla Balcárková, Petr Dresler, Jiří Macháček, Michaela Prišťáková",
    "authors": [
      "Adéla Balcárková",
      "Petr Dresler",
      "Jiří Macháček",
      "Michaela Prišťáková"
    ],
    "date": "2026-05-06T07:09:00.083628+00:00"
  },
  {
    "title": "Mému mladšímu já",
    "url": "https://www.kosmas.cz/knihy/568598/memu-mladsimu-ja/",
    "description": "Mému mladšímu já - Lucie Lešková",
    "authors": [
      "Lucie Lešková"
    ],
    "date": "2026-05-06T07:08:59.083628+00:00"
  },
  {
    "title": "Strážce svaté relikvie",
    "url": "https://www.kosmas.cz/knihy/568599/strazce-svate-relikvie/",
    "description": "Strážce svaté relikvie - František Kalenda",
    "authors": [
      "František Kalenda"
    ],
    "date": "2026-05-06T07:08:58.083628+00:00"
  },
  {
    "title": "Hry, sítě, porno",
    "url": "https://www.kosmas.cz/knihy/568618/hry-site-porno/",
    "description": "Hry, sítě, porno - Michaela Slussareff",
    "authors": [
      "Michaela Slussareff"
    ],
    "date": "2026-05-06T07:08:56.083628+00:00"
  },
  {
    "title": "Popelčina velká noc",
    "url": "https://www.kosmas.cz/knihy/568622/popelcina-velka-noc/",
    "description": "Popelčina velká noc - Michelle Smartová",
    "authors": [
      "Michelle Smartová"
    ],
    "date": "2026-05-06T07:08:55.083628+00:00"
  },
  {
    "title": "Napravený nepřítel",
    "url": "https://www.kosmas.cz/knihy/568623/napraveny-nepritel/",
    "description": "Napravený nepřítel - Jennifer Haywardová",
    "authors": [
      "Jennifer Haywardová"
    ],
    "date": "2026-05-06T07:08:54.083628+00:00"
  },
  {
    "title": "Pomsta po řecku",
    "url": "https://www.kosmas.cz/knihy/568625/pomsta-po-recku/",
    "description": "Pomsta po řecku - Maya Blakeová",
    "authors": [
      "Maya Blakeová"
    ],
    "date": "2026-05-06T07:08:53.083628+00:00"
  },
  {
    "title": "Dědic říše",
    "url": "https://www.kosmas.cz/knihy/568626/dedic-rise/",
    "description": "Dědic říše - Abby Greenová",
    "authors": [
      "Abby Greenová"
    ],
    "date": "2026-05-06T07:08:52.083628+00:00"
  },
  {
    "title": "Nedovolené potěšení slečny Claiborneové",
    "url": "https://www.kosmas.cz/knihy/568627/nedovolene-poteseni-slecny-claiborneove/",
    "description": "Nedovolené potěšení slečny Claiborneové - Bronwyn Scottová",
    "authors": [
      "Bronwyn Scottová"
    ],
    "date": "2026-05-06T07:08:51.083628+00:00"
  },
  {
    "title": "Dáma s maskou",
    "url": "https://www.kosmas.cz/knihy/568628/dama-s-maskou/",
    "description": "Dáma s maskou - Diane Gastonová",
    "authors": [
      "Diane Gastonová"
    ],
    "date": "2026-05-06T07:08:50.083628+00:00"
  },
  {
    "title": "Co manželka nevěděla",
    "url": "https://www.kosmas.cz/knihy/568629/co-manzelka-nevedela/",
    "description": "Co manželka nevěděla - Kelly Hunterová",
    "authors": [
      "Kelly Hunterová"
    ],
    "date": "2026-05-06T07:08:49.083628+00:00"
  },
  {
    "title": "Penzion v Portugalsku",
    "url": "https://www.kosmas.cz/knihy/568630/penzion-v-portugalsku/",
    "description": "Penzion v Portugalsku - Julie Caplinová",
    "authors": [
      "Julie Caplinová"
    ],
    "date": "2026-05-06T07:08:48.083628+00:00"
  },
  {
    "title": "Marný boj",
    "url": "https://www.kosmas.cz/knihy/568631/marny-boj/",
    "description": "Marný boj - Fiona Brandová",
    "authors": [
      "Fiona Brandová"
    ],
    "date": "2026-05-06T07:08:47.083628+00:00"
  },
  {
    "title": "Nakonec lásku našli",
    "url": "https://www.kosmas.cz/knihy/568632/nakonec-lasku-nasli/",
    "description": "Nakonec lásku našli - Lynne Grahamová",
    "authors": [
      "Lynne Grahamová"
    ],
    "date": "2026-05-06T07:08:46.083628+00:00"
  },
  {
    "title": "Klíče k volnosti",
    "url": "https://www.kosmas.cz/knihy/225808/klice-k-volnosti/",
    "description": "Klíče k volnosti - André Breton",
    "authors": [
      "André Breton"
    ],
    "date": "2026-05-05T06:59:14.146353+00:00"
  },
  {
    "title": "Volání po vzpouře",
    "url": "https://www.kosmas.cz/knihy/568202/volani-po-vzpoure/",
    "description": "Volání po vzpouře - David Weber, Timothy Zahn, Thomas Pope",
    "authors": [
      "David Weber",
      "Timothy Zahn",
      "Thomas Pope"
    ],
    "date": "2026-05-05T06:59:13.146353+00:00"
  },
  {
    "title": "Spokojené tělo po padesátce",
    "url": "https://www.kosmas.cz/knihy/567270/spokojene-telo-po-padesatce/",
    "description": "Spokojené tělo po padesátce - Will Harlow",
    "authors": [
      "Will Harlow"
    ],
    "date": "2026-05-05T06:59:12.146353+00:00"
  },
  {
    "title": "Zlomené duše",
    "url": "https://www.kosmas.cz/knihy/568438/zlomene-duse/",
    "description": "Zlomené duše - Dysmas de Lassus",
    "authors": [
      "Dysmas de Lassus"
    ],
    "date": "2026-05-05T06:59:11.146353+00:00"
  },
  {
    "title": "Káčko, kafíčko a konec světa",
    "url": "https://www.kosmas.cz/knihy/568489/kacko-kaficko-a-konec-sveta/",
    "description": "Káčko, kafíčko a konec světa - Martin Paur",
    "authors": [
      "Martin Paur"
    ],
    "date": "2026-05-05T06:59:10.146353+00:00"
  },
  {
    "title": "Autismus a náročné chování",
    "url": "https://www.kosmas.cz/knihy/567553/autismus-a-narocne-chovani/",
    "description": "Autismus a náročné chování - Petra Mertinová, Tony Osgood",
    "authors": [
      "Petra Mertinová",
      "Tony Osgood"
    ],
    "date": "2026-05-05T06:59:09.146353+00:00"
  },
  {
    "title": "Wednesday: Oficiální omalovánky",
    "url": "https://www.kosmas.cz/knihy/567559/wednesday-oficialni-omalovanky/",
    "description": "Wednesday: Oficiální omalovánky - Mike Meskin",
    "authors": [
      "Mike Meskin"
    ],
    "date": "2026-05-05T06:59:08.146353+00:00"
  },
  {
    "title": "Autoatlas Česko Slovensko 2026/27",
    "url": "https://www.kosmas.cz/knihy/568546/autoatlas-cesko-slovensko-2026-27/",
    "description": "Autoatlas Česko Slovensko 2026/27",
    "authors": [],
    "date": "2026-05-05T06:59:07.146353+00:00"
  },
  {
    "title": "Francois Villon",
    "url": "https://www.kosmas.cz/knihy/566095/francois-villon/",
    "description": "Francois Villon - Jean Favier",
    "authors": [
      "Jean Favier"
    ],
    "date": "2026-05-05T06:59:06.146353+00:00"
  },
  {
    "title": "Medvídek Pú  - Malá kniha velkých mouder",
    "url": "https://www.kosmas.cz/knihy/566124/medvidek-pu-mala-kniha-velkych-mouder/",
    "description": "Medvídek Pú  - Malá kniha velkých mouder - kolektiv",
    "authors": [
      "kolektiv"
    ],
    "date": "2026-05-05T06:59:05.146353+00:00"
  },
  {
    "title": "Rudé město",
    "url": "https://www.kosmas.cz/knihy/566155/rude-mesto/",
    "description": "Rudé město - Marie Lu",
    "authors": [
      "Marie Lu"
    ],
    "date": "2026-05-05T06:59:04.146353+00:00"
  },
  {
    "title": "Star Wars - Mandalorian a Grogu - Nové dobrodružství",
    "url": "https://www.kosmas.cz/knihy/566160/star-wars-mandalorian-a-grogu-nove-dobrodruzstvi/",
    "description": "Star Wars - Mandalorian a Grogu - Nové dobrodružství - kolektiv",
    "authors": [
      "kolektiv"
    ],
    "date": "2026-05-05T06:59:03.146353+00:00"
  },
  {
    "title": "Tajemství nadlidské síly",
    "url": "https://www.kosmas.cz/knihy/566162/tajemstvi-nadlidske-sily/",
    "description": "Tajemství nadlidské síly - Alison Bechdel",
    "authors": [
      "Alison Bechdel"
    ],
    "date": "2026-05-05T06:59:02.146353+00:00"
  },
  {
    "title": "Legenda",
    "url": "https://www.kosmas.cz/knihy/566250/legenda/",
    "description": "Legenda - David Gemmell",
    "authors": [
      "David Gemmell"
    ],
    "date": "2026-05-05T06:59:01.146353+00:00"
  },
  {
    "title": "O nás zvířatech",
    "url": "https://www.kosmas.cz/knihy/565873/o-nas-zviratech/",
    "description": "O nás zvířatech - Lukáš Fišer",
    "authors": [
      "Lukáš Fišer"
    ],
    "date": "2026-05-05T06:59:00.146353+00:00"
  },
  {
    "title": "Maková pole",
    "url": "https://www.kosmas.cz/knihy/565874/makova-pole/",
    "description": "Maková pole - Nikki Erlick",
    "authors": [
      "Nikki Erlick"
    ],
    "date": "2026-05-05T06:58:59.146353+00:00"
  },
  {
    "title": "Amanda Blacková: Ztracený amulet",
    "url": "https://www.kosmas.cz/knihy/565876/amanda-blackova-ztraceny-amulet/",
    "description": "Amanda Blacková: Ztracený amulet - Juan Gómez-Jurado, Barbara Montes",
    "authors": [
      "Juan Gómez-Jurado",
      "Barbara Montes"
    ],
    "date": "2026-05-05T06:58:58.146353+00:00"
  },
  {
    "title": "Rod bijících srdcí",
    "url": "https://www.kosmas.cz/knihy/565877/rod-bijicich-srdci/",
    "description": "Rod bijících srdcí - Olivia Wildenstein",
    "authors": [
      "Olivia Wildenstein"
    ],
    "date": "2026-05-05T06:58:57.146353+00:00"
  },
  {
    "title": "Pýcha a předsudek - grafický román",
    "url": "https://www.kosmas.cz/knihy/565878/pycha-a-predsudek-graficky-roman/",
    "description": "Pýcha a předsudek - grafický román - Jane Austenová, Claudia Kühn, Tara Spruit",
    "authors": [
      "Jane Austenová",
      "Claudia Kühn",
      "Tara Spruit"
    ],
    "date": "2026-05-05T06:58:56.146353+00:00"
  },
  {
    "title": "Na zlaté hraně",
    "url": "https://www.kosmas.cz/knihy/565880/na-zlate-hrane/",
    "description": "Na zlaté hraně - Layne Fargo",
    "authors": [
      "Layne Fargo"
    ],
    "date": "2026-05-05T06:58:55.146353+00:00"
  },
  {
    "title": "Balonky zakázány",
    "url": "https://www.kosmas.cz/knihy/568440/balonky-zakazany/",
    "description": "Balonky zakázány - Robert Zola Christensen",
    "authors": [
      "Robert Zola Christensen"
    ],
    "date": "2026-05-02T06:50:44.613627+00:00"
  },
  {
    "title": "Emilie a 121. patro",
    "url": "https://www.kosmas.cz/knihy/568456/emilie-a-121.-patro/",
    "description": "Emilie a 121. patro - Martina Macháčová",
    "authors": [
      "Martina Macháčová"
    ],
    "date": "2026-05-02T06:50:43.613627+00:00"
  },
  {
    "title": "Beatles - kompletní příběh",
    "url": "https://www.kosmas.cz/knihy/568507/beatles-kompletni-pribeh/",
    "description": "Beatles - kompletní příběh - kol.",
    "authors": [
      "kol."
    ],
    "date": "2026-05-02T06:50:42.613627+00:00"
  },
  {
    "title": "Nazývačka",
    "url": "https://www.kosmas.cz/knihy/568538/nazyvacka/",
    "description": "Nazývačka - Jedediah Berry",
    "authors": [
      "Jedediah Berry"
    ],
    "date": "2026-05-02T06:50:40.613627+00:00"
  },
  {
    "title": "Kruh dní",
    "url": "https://www.kosmas.cz/knihy/568540/kruh-dni/",
    "description": "Kruh dní - Ken Follett",
    "authors": [
      "Ken Follett"
    ],
    "date": "2026-05-02T06:50:39.613627+00:00"
  },
  {
    "title": "Saving 6",
    "url": "https://www.kosmas.cz/knihy/568541/saving-6/",
    "description": "Saving 6 - Chloe Walsh",
    "authors": [
      "Chloe Walsh"
    ],
    "date": "2026-05-02T06:50:38.613627+00:00"
  },
  {
    "title": "Černý sněhulák",
    "url": "https://www.kosmas.cz/knihy/568543/cerny-snehulak/",
    "description": "Černý sněhulák - Marie Jakoubková",
    "authors": [
      "Marie Jakoubková"
    ],
    "date": "2026-05-02T06:50:37.613627+00:00"
  },
  {
    "title": "Dotek břečťanu",
    "url": "https://www.kosmas.cz/knihy/568544/dotek-brectanu/",
    "description": "Dotek břečťanu - Ivy Green",
    "authors": [
      "Ivy Green"
    ],
    "date": "2026-05-02T06:50:36.613627+00:00"
  },
  {
    "title": "Meze růstu",
    "url": "https://www.kosmas.cz/knihy/567288/meze-rustu/",
    "description": "Meze růstu - William W. Behrens III., Dennis L. Meadows, Donella H. Meadowsová, Jørgen Randers",
    "authors": [
      "William W. Behrens III.",
      "Dennis L. Meadows",
      "Donella H. Meadowsová",
      "Jørgen Randers"
    ],
    "date": "2026-05-02T06:50:35.613627+00:00"
  },
  {
    "title": "Bezlepková kuchařka",
    "url": "https://www.kosmas.cz/knihy/567266/bezlepkova-kucharka/",
    "description": "Bezlepková kuchařka - Zdeňka Mazúrová",
    "authors": [
      "Zdeňka Mazúrová"
    ],
    "date": "2026-05-01T07:07:06.178046+00:00"
  },
  {
    "title": "Bezlepkové slavnosti - Sváteční menu nejen pro celiaky",
    "url": "https://www.kosmas.cz/knihy/567313/bezlepkove-slavnosti-svatecni-menu-nejen-pro-celiaky/",
    "description": "Bezlepkové slavnosti - Sváteční menu nejen pro celiaky - Zdeňka Mazúrová",
    "authors": [
      "Zdeňka Mazúrová"
    ],
    "date": "2026-05-01T07:07:05.178046+00:00"
  },
  {
    "title": "Bezlepkové pečení pro každého",
    "url": "https://www.kosmas.cz/knihy/567316/bezlepkove-peceni-pro-kazdeho/",
    "description": "Bezlepkové pečení pro každého - Zdeňka Mazúrová",
    "authors": [
      "Zdeňka Mazúrová"
    ],
    "date": "2026-05-01T07:07:04.178046+00:00"
  },
  {
    "title": "Ateliér radostné tvorby. Atelier of Joyful Creativity in Prague",
    "url": "https://www.kosmas.cz/knihy/567689/atelier-radostne-tvorby.-atelier-of-joyful-creativity-in-prague/",
    "description": "Ateliér radostné tvorby. Atelier of Joyful Creativity in Prague - Piot Gierowski, Jan H. Vitvar, Vladimír Drábek, Jaromír Typlt",
    "authors": [
      "Piot Gierowski",
      "Jan H. Vitvar",
      "Vladimír Drábek",
      "Jaromír Typlt"
    ],
    "date": "2026-05-01T07:07:00.178046+00:00"
  },
  {
    "title": "Anatomie lži",
    "url": "https://www.kosmas.cz/knihy/567798/anatomie-lzi/",
    "description": "Anatomie lži - Dan Brown",
    "authors": [
      "Dan Brown"
    ],
    "date": "2026-05-01T07:06:59.178046+00:00"
  },
  {
    "title": "Knížka do kočárku - Koťátko a kamarádi",
    "url": "https://www.kosmas.cz/knihy/567989/knizka-do-kocarku-kotatko-a-kamaradi/",
    "description": "Knížka do kočárku - Koťátko a kamarádi",
    "authors": [],
    "date": "2026-05-01T07:06:58.178046+00:00"
  },
  {
    "title": "Město duchů",
    "url": "https://www.kosmas.cz/knihy/567996/mesto-duchu/",
    "description": "Město duchů - Kevin Chen",
    "authors": [
      "Kevin Chen"
    ],
    "date": "2026-05-01T07:06:57.178046+00:00"
  },
  {
    "title": "Až dohraje černej vinyl",
    "url": "https://www.kosmas.cz/knihy/568232/az-dohraje-cernej-vinyl/",
    "description": "Až dohraje černej vinyl - Zdeněk Lebl",
    "authors": [
      "Zdeněk Lebl"
    ],
    "date": "2026-05-01T07:06:54.178046+00:00"
  },
  {
    "title": "Básně do Slezska II",
    "url": "https://www.kosmas.cz/knihy/568233/basne-do-slezska-ii/",
    "description": "Básně do Slezska II - Břetislav Pletnicki",
    "authors": [
      "Břetislav Pletnicki"
    ],
    "date": "2026-05-01T07:06:53.178046+00:00"
  },
  {
    "title": "Jiné básně",
    "url": "https://www.kosmas.cz/knihy/568237/jine-basne/",
    "description": "Jiné básně - Břetislav Pletnicki",
    "authors": [
      "Břetislav Pletnicki"
    ],
    "date": "2026-05-01T07:06:51.178046+00:00"
  },
  {
    "title": "SONETISSIMO",
    "url": "https://www.kosmas.cz/knihy/568239/sonetissimo/",
    "description": "SONETISSIMO - Zdeněk Lebl",
    "authors": [
      "Zdeněk Lebl"
    ],
    "date": "2026-05-01T07:06:50.178046+00:00"
  },
  {
    "title": "Víra vrytá pod kůži",
    "url": "https://www.kosmas.cz/knihy/568283/vira-vryta-pod-kuzi/",
    "description": "Víra vrytá pod kůži - Martin Drlíček, Zuzana Faktorová Frantová",
    "authors": [
      "Martin Drlíček",
      "Zuzana Faktorová Frantová"
    ],
    "date": "2026-05-01T07:06:48.178046+00:00"
  },
  {
    "title": "Kontexty 2/2026",
    "url": "https://www.kosmas.cz/knihy/568424/kontexty-2-2026/",
    "description": "Kontexty 2/2026",
    "authors": [],
    "date": "2026-05-01T07:06:47.178046+00:00"
  },
  {
    "title": "Můj stát. Putování s českým lvem za sedmi státními symboly",
    "url": "https://www.kosmas.cz/knihy/566847/muj-stat.-putovani-s-ceskym-lvem-za-sedmi-statnimi-symboly/",
    "description": "Můj stát. Putování s českým lvem za sedmi státními symboly - Martin Velíšek",
    "authors": [
      "Martin Velíšek"
    ],
    "date": "2026-04-30T07:05:24.475028+00:00"
  },
  {
    "title": "Helena Zmatlíková dětem",
    "url": "https://www.kosmas.cz/knihy/566239/helena-zmatlikova-detem/",
    "description": "Helena Zmatlíková dětem - Helena Zmatlíková",
    "authors": [
      "Helena Zmatlíková"
    ],
    "date": "2026-04-30T07:05:23.475028+00:00"
  },
  {
    "title": "Kočka na kolejích",
    "url": "https://www.kosmas.cz/knihy/567400/kocka-na-kolejich/",
    "description": "Kočka na kolejích - Josef Topol",
    "authors": [
      "Josef Topol"
    ],
    "date": "2026-04-30T07:05:22.475028+00:00"
  },
  {
    "title": "Hodinový hoteliér",
    "url": "https://www.kosmas.cz/knihy/567401/hodinovy-hotelier/",
    "description": "Hodinový hoteliér - Pavel Landovský",
    "authors": [
      "Pavel Landovský"
    ],
    "date": "2026-04-30T07:05:21.475028+00:00"
  },
  {
    "title": "Matematika plná koroptví",
    "url": "https://www.kosmas.cz/knihy/567484/matematika-plna-koroptvi/",
    "description": "Matematika plná koroptví - Milena Fucimanová",
    "authors": [
      "Milena Fucimanová"
    ],
    "date": "2026-04-30T07:05:20.475028+00:00"
  },
  {
    "title": "Brutlyrik",
    "url": "https://www.kosmas.cz/knihy/568195/brutlyrik/",
    "description": "Brutlyrik - Jaroslav Švadlena",
    "authors": [
      "Jaroslav Švadlena"
    ],
    "date": "2026-04-30T07:05:19.475028+00:00"
  },
  {
    "title": "Dharmašlap",
    "url": "https://www.kosmas.cz/knihy/568197/dharmaslap/",
    "description": "Dharmašlap - Jaroslav Švadlena",
    "authors": [
      "Jaroslav Švadlena"
    ],
    "date": "2026-04-30T07:05:18.475028+00:00"
  },
  {
    "title": "Hegemonie a marginalita ve slovanském areálu",
    "url": "https://www.kosmas.cz/knihy/568235/hegemonie-a-marginalita-ve-slovanskem-arealu/",
    "description": "Hegemonie a marginalita ve slovanském areálu - Jan Dubecký, Marek Příhoda, Cyril Šolle",
    "authors": [
      "Jan Dubecký",
      "Marek Příhoda",
      "Cyril Šolle"
    ],
    "date": "2026-04-30T07:05:17.475028+00:00"
  },
  {
    "title": "Případ výjimečné klibny",
    "url": "https://www.kosmas.cz/knihy/568263/pripad-vyjimecne-klibny/",
    "description": "Případ výjimečné klibny - Jaroslav Velinský",
    "authors": [
      "Jaroslav Velinský"
    ],
    "date": "2026-04-30T07:05:16.475028+00:00"
  },
  {
    "title": "Kronika druhé světové války",
    "url": "https://www.kosmas.cz/knihy/555546/kronika-druhe-svetove-valky/",
    "description": "Kronika druhé světové války - František Emmert",
    "authors": [
      "František Emmert"
    ],
    "date": "2026-04-30T07:05:15.475028+00:00"
  },
  {
    "title": "Gianluigi Buffon: umění pádů",
    "url": "https://www.kosmas.cz/knihy/566096/gianluigi-buffon-umeni-padu/",
    "description": "Gianluigi Buffon: umění pádů - Gianluigi Buffon",
    "authors": [
      "Gianluigi Buffon"
    ],
    "date": "2026-04-30T07:05:14.475028+00:00"
  },
  {
    "title": "Marvel - Spidey a jeho úžasní přátelé: Odvážná záchrana",
    "url": "https://www.kosmas.cz/knihy/566123/marvel-spidey-a-jeho-uzasni-pratele-odvazna-zachrana/",
    "description": "Marvel - Spidey a jeho úžasní přátelé: Odvážná záchrana - kolektiv",
    "authors": [
      "kolektiv"
    ],
    "date": "2026-04-30T07:05:13.475028+00:00"
  },
  {
    "title": "Mezi nebem a zemí",
    "url": "https://www.kosmas.cz/knihy/566125/mezi-nebem-a-zemi/",
    "description": "Mezi nebem a zemí - Mariana Zapata",
    "authors": [
      "Mariana Zapata"
    ],
    "date": "2026-04-30T07:05:12.475028+00:00"
  },
  {
    "title": "Orlík",
    "url": "https://www.kosmas.cz/knihy/566140/orlik/",
    "description": "Orlík - Lucie Bechynková, Jan Štoček",
    "authors": [
      "Lucie Bechynková",
      "Jan Štoček"
    ],
    "date": "2026-04-30T07:05:11.475028+00:00"
  },
  {
    "title": "Volná jízda",
    "url": "https://www.kosmas.cz/knihy/566793/volna-jizda/",
    "description": "Volná jízda - Bal Khabra",
    "authors": [
      "Bal Khabra"
    ],
    "date": "2026-04-30T07:05:10.475028+00:00"
  },
  {
    "title": "Víc než pomsta",
    "url": "https://www.kosmas.cz/knihy/566167/vic-nez-pomsta/",
    "description": "Víc než pomsta - R. A. Smyth",
    "authors": [
      "R. A. Smyth"
    ],
    "date": "2026-04-30T07:05:09.475028+00:00"
  },
  {
    "title": "Vražda v knihkupectví",
    "url": "https://www.kosmas.cz/knihy/566169/vrazda-v-knihkupectvi/",
    "description": "Vražda v knihkupectví - Ellie Alexander",
    "authors": [
      "Ellie Alexander"
    ],
    "date": "2026-04-30T07:05:08.475028+00:00"
  },
  {
    "title": "Za pohádkou s vodníkem Leknínkem",
    "url": "https://www.kosmas.cz/knihy/566171/za-pohadkou-s-vodnikem-lekninkem/",
    "description": "Za pohádkou s vodníkem Leknínkem - Iva Hoňková",
    "authors": [
      "Iva Hoňková"
    ],
    "date": "2026-04-30T07:05:07.475028+00:00"
  },
  {
    "title": "Tam, kde štěkají kočky",
    "url": "https://www.kosmas.cz/knihy/566856/tam-kde-stekaji-kocky/",
    "description": "Tam, kde štěkají kočky - Stanislav Beran",
    "authors": [
      "Stanislav Beran"
    ],
    "date": "2026-04-30T07:05:06.475028+00:00"
  },
  {
    "title": "Koťátko Cesmína - Jasmínčina zvířátka",
    "url": "https://www.kosmas.cz/knihy/566932/kotatko-cesmina-jasmincina-zviratka/",
    "description": "Koťátko Cesmína - Jasmínčina zvířátka - Helen Petersová",
    "authors": [
      "Helen Petersová"
    ],
    "date": "2026-04-30T07:05:05.475028+00:00"
  },
  {
    "title": "Nezbedné obrázky - modrý sešit",
    "url": "https://www.kosmas.cz/knihy/568251/nezbedne-obrazky-modry-sesit/",
    "description": "Nezbedné obrázky - modrý sešit",
    "authors": [],
    "date": "2026-04-29T07:02:55.192449+00:00"
  },
  {
    "title": "Radost z učení",
    "url": "https://www.kosmas.cz/knihy/567543/radost-z-uceni/",
    "description": "Radost z učení - Aletha Solterová",
    "authors": [
      "Aletha Solterová"
    ],
    "date": "2026-04-29T07:02:54.192449+00:00"
  },
  {
    "title": "Přístup zaměřený na člověka",
    "url": "https://www.kosmas.cz/knihy/567544/pristup-zamereny-na-cloveka/",
    "description": "Přístup zaměřený na člověka - Petr Mikoška",
    "authors": [
      "Petr Mikoška"
    ],
    "date": "2026-04-29T07:02:53.192449+00:00"
  },
  {
    "title": "Srdeční selhání",
    "url": "https://www.kosmas.cz/knihy/568471/srdecni-selhani/",
    "description": "Srdeční selhání - Filip Málek, Petr Neužil, Martin Polák, kolektiv",
    "authors": [
      "Filip Málek",
      "Petr Neužil",
      "Martin Polák",
      "kolektiv"
    ],
    "date": "2026-04-29T07:02:52.192449+00:00"
  },
  {
    "title": "Řeznice z Malé Barmy",
    "url": "https://www.kosmas.cz/knihy/568476/reznice-z-male-barmy/",
    "description": "Řeznice z Malé Barmy - Hakan Nesser",
    "authors": [
      "Hakan Nesser"
    ],
    "date": "2026-04-29T07:02:51.192449+00:00"
  },
  {
    "title": "Město duchů",
    "url": "https://www.kosmas.cz/knihy/568480/mesto-duchu/",
    "description": "Město duchů - Kevin Chen",
    "authors": [
      "Kevin Chen"
    ],
    "date": "2026-04-29T07:02:50.192449+00:00"
  },
  {
    "title": "Výzvy a inovace v sociální práci se seniory",
    "url": "https://www.kosmas.cz/knihy/568483/vyzvy-a-inovace-v-socialni-praci-se-seniory/",
    "description": "Výzvy a inovace v sociální práci se seniory - Helena Machulová, Lenka Žižka Motlová",
    "authors": [
      "Helena Machulová",
      "Lenka Žižka Motlová"
    ],
    "date": "2026-04-29T07:02:49.192449+00:00"
  },
  {
    "title": "Sladké očekávání",
    "url": "https://www.kosmas.cz/knihy/568485/sladke-ocekavani/",
    "description": "Sladké očekávání - Hannah Lynn",
    "authors": [
      "Hannah Lynn"
    ],
    "date": "2026-04-29T07:02:48.192449+00:00"
  },
  {
    "title": "Od prince ke králi",
    "url": "https://www.kosmas.cz/knihy/568487/od-prince-ke-krali/",
    "description": "Od prince ke králi - Jan František Bím",
    "authors": [
      "Jan František Bím"
    ],
    "date": "2026-04-29T07:02:47.192449+00:00"
  },
  {
    "title": "Ulička tajných vášní - Skandální lady Constance",
    "url": "https://www.kosmas.cz/knihy/567835/ulicka-tajnych-vasni-skandalni-lady-constance/",
    "description": "Ulička tajných vášní - Skandální lady Constance - Scarlett Peckham",
    "authors": [
      "Scarlett Peckham"
    ],
    "date": "2026-04-29T07:02:46.192449+00:00"
  },
  {
    "title": "Eliška Andílek",
    "url": "https://www.kosmas.cz/knihy/568490/eliska-andilek/",
    "description": "Eliška Andílek - Pavlína Jurková",
    "authors": [
      "Pavlína Jurková"
    ],
    "date": "2026-04-29T07:02:45.192449+00:00"
  },
  {
    "title": "Šumavský upír",
    "url": "https://www.kosmas.cz/knihy/567771/sumavsky-upir/",
    "description": "Šumavský upír - Miloslav Švandrlík",
    "authors": [
      "Miloslav Švandrlík"
    ],
    "date": "2026-04-29T07:02:44.192449+00:00"
  },
  {
    "title": "Domov zlatem spravený",
    "url": "https://www.kosmas.cz/knihy/565138/domov-zlatem-spraveny/",
    "description": "Domov zlatem spravený - Sanae Hošio",
    "authors": [
      "Sanae Hošio"
    ],
    "date": "2026-04-29T07:02:43.192449+00:00"
  },
  {
    "title": "Ostrov země",
    "url": "https://www.kosmas.cz/knihy/565431/ostrov-zeme/",
    "description": "Ostrov země - Futurum",
    "authors": [
      "Futurum"
    ],
    "date": "2026-04-29T07:02:42.192449+00:00"
  },
  {
    "title": "Dědictví skotských templářů",
    "url": "https://www.kosmas.cz/knihy/563143/dedictvi-skotskych-templaru/",
    "description": "Dědictví skotských templářů - Vlastimil Vondruška",
    "authors": [
      "Vlastimil Vondruška"
    ],
    "date": "2026-04-29T07:02:41.192449+00:00"
  },
  {
    "title": "První Evropané",
    "url": "https://www.kosmas.cz/knihy/550424/prvni-evropane/",
    "description": "První Evropané - Jan Turek",
    "authors": [
      "Jan Turek"
    ],
    "date": "2026-04-29T07:02:40.192449+00:00"
  },
  {
    "title": "Přítelkyně paní Maigretové",
    "url": "https://www.kosmas.cz/knihy/568006/pritelkyne-pani-maigretove/",
    "description": "Přítelkyně paní Maigretové - Georges Simenon",
    "authors": [
      "Georges Simenon"
    ],
    "date": "2026-04-29T07:02:39.192449+00:00"
  },
  {
    "title": "Moře času",
    "url": "https://www.kosmas.cz/knihy/568037/more-casu/",
    "description": "Moře času - Jiří Žáček",
    "authors": [
      "Jiří Žáček"
    ],
    "date": "2026-04-29T07:02:38.192449+00:00"
  },
  {
    "title": "KáPéZetka Ne-mu-síš",
    "url": "https://www.kosmas.cz/knihy/568095/kapezetka-ne-mu-sis/",
    "description": "KáPéZetka Ne-mu-síš - Kateřina Šťastná",
    "authors": [
      "Kateřina Šťastná"
    ],
    "date": "2026-04-29T07:02:37.192449+00:00"
  },
  {
    "title": "Naprosté motivy",
    "url": "https://www.kosmas.cz/knihy/568133/naproste-motivy/",
    "description": "Naprosté motivy - Josef Mlejnek st.",
    "authors": [
      "Josef Mlejnek st."
    ],
    "date": "2026-04-28T07:07:59.729387+00:00"
  },
  {
    "title": "Ke startu připravit!",
    "url": "https://www.kosmas.cz/knihy/567977/ke-startu-pripravit/",
    "description": "Ke startu připravit! - Przemek Liput",
    "authors": [
      "Przemek Liput"
    ],
    "date": "2026-04-28T07:07:58.729387+00:00"
  },
  {
    "title": "Právní biografie jednoho fideikomisu",
    "url": "https://www.kosmas.cz/knihy/568217/pravni-biografie-jednoho-fideikomisu/",
    "description": "Právní biografie jednoho fideikomisu - Michal Novotný",
    "authors": [
      "Michal Novotný"
    ],
    "date": "2026-04-28T07:07:57.729387+00:00"
  },
  {
    "title": "Dědictví",
    "url": "https://www.kosmas.cz/knihy/568363/dedictvi/",
    "description": "Dědictví - Moa Herngren",
    "authors": [
      "Moa Herngren"
    ],
    "date": "2026-04-28T07:07:55.729387+00:00"
  },
  {
    "title": "Umění rozhodnout se",
    "url": "https://www.kosmas.cz/knihy/566507/umeni-rozhodnout-se/",
    "description": "Umění rozhodnout se - Tereza Sladká",
    "authors": [
      "Tereza Sladká"
    ],
    "date": "2026-04-28T07:07:53.729387+00:00"
  },
  {
    "title": "Poruchy chůze a stability",
    "url": "https://www.kosmas.cz/knihy/568366/poruchy-chuze-a-stability/",
    "description": "Poruchy chůze a stability - Ota Gál, Martina Hoskovcová, Evžen Růžička, kolektiv",
    "authors": [
      "Ota Gál",
      "Martina Hoskovcová",
      "Evžen Růžička",
      "kolektiv"
    ],
    "date": "2026-04-28T07:07:52.729387+00:00"
  },
  {
    "title": "Malý kousek Paříže",
    "url": "https://www.kosmas.cz/knihy/568367/maly-kousek-parize/",
    "description": "Malý kousek Paříže - Adéla Mervartová",
    "authors": [
      "Adéla Mervartová"
    ],
    "date": "2026-04-28T07:07:51.729387+00:00"
  },
  {
    "title": "Červ",
    "url": "https://www.kosmas.cz/knihy/568370/cerv/",
    "description": "Červ - František Kozmon",
    "authors": [
      "František Kozmon"
    ],
    "date": "2026-04-28T07:07:48.729387+00:00"
  },
  {
    "title": "Od deníků k výzkumu",
    "url": "https://www.kosmas.cz/knihy/568371/od-deniku-k-vyzkumu/",
    "description": "Od deníků k výzkumu - Lucie Jarkovská, Martina Nosková",
    "authors": [
      "Lucie Jarkovská",
      "Martina Nosková"
    ],
    "date": "2026-04-28T07:07:47.729387+00:00"
  },
  {
    "title": "Frankenstein",
    "url": "https://www.kosmas.cz/knihy/568372/frankenstein/",
    "description": "Frankenstein - Gemma Barder, Mary Shelleyová",
    "authors": [
      "Gemma Barder",
      "Mary Shelleyová"
    ],
    "date": "2026-04-28T07:07:46.729387+00:00"
  },
  {
    "title": "Čína - Císařova závěť",
    "url": "https://www.kosmas.cz/knihy/568375/cina-cisarova-zavet/",
    "description": "Čína - Císařova závěť - Veronika Válková",
    "authors": [
      "Veronika Válková"
    ],
    "date": "2026-04-28T07:07:44.729387+00:00"
  },
  {
    "title": "Stanley Tucci: U jednoho stolu",
    "url": "https://www.kosmas.cz/knihy/566413/stanley-tucci-u-jednoho-stolu/",
    "description": "Stanley Tucci: U jednoho stolu - Stanley Tucci",
    "authors": [
      "Stanley Tucci"
    ],
    "date": "2026-04-28T07:07:42.729387+00:00"
  },
  {
    "title": "Můj první hrabě",
    "url": "https://www.kosmas.cz/knihy/567229/muj-prvni-hrabe/",
    "description": "Můj první hrabě - Ella Quinnová",
    "authors": [
      "Ella Quinnová"
    ],
    "date": "2026-04-28T07:07:41.729387+00:00"
  },
  {
    "title": "Vyděšená k smrti",
    "url": "https://www.kosmas.cz/knihy/568288/vydesena-k-smrti/",
    "description": "Vyděšená k smrti - Rachel Amphlett",
    "authors": [
      "Rachel Amphlett"
    ],
    "date": "2026-04-27T07:08:28.900650+00:00"
  },
  {
    "title": "Kouzla náhody",
    "url": "https://www.kosmas.cz/knihy/567853/kouzla-nahody/",
    "description": "Kouzla náhody - Lenka Flášarová",
    "authors": [
      "Lenka Flášarová"
    ],
    "date": "2026-04-27T07:08:27.900650+00:00"
  },
  {
    "title": "Atopický ekzém",
    "url": "https://www.kosmas.cz/knihy/568311/atopicky-ekzem/",
    "description": "Atopický ekzém - Věra Pekárková Zíková",
    "authors": [
      "Věra Pekárková Zíková"
    ],
    "date": "2026-04-27T07:08:17.900650+00:00"
  },
  {
    "title": "Juditino tajemství",
    "url": "https://www.kosmas.cz/knihy/568312/juditino-tajemstvi/",
    "description": "Juditino tajemství - Veronika Moreira",
    "authors": [
      "Veronika Moreira"
    ],
    "date": "2026-04-27T07:08:16.900650+00:00"
  },
  {
    "title": "Golem 02/2026",
    "url": "https://www.kosmas.cz/knihy/568313/golem-02-2026/",
    "description": "Golem 02/2026",
    "authors": [],
    "date": "2026-04-27T07:08:15.900650+00:00"
  },
  {
    "title": "Války s odpadem",
    "url": "https://www.kosmas.cz/knihy/565769/valky-s-odpadem/",
    "description": "Války s odpadem - Alexander Clapp",
    "authors": [
      "Alexander Clapp"
    ],
    "date": "2026-04-27T07:08:14.900650+00:00"
  },
  {
    "title": "Věda o pomstě",
    "url": "https://www.kosmas.cz/knihy/568316/veda-o-pomste/",
    "description": "Věda o pomstě - James Kimmel jr.",
    "authors": [
      "James Kimmel jr."
    ],
    "date": "2026-04-27T07:08:13.900650+00:00"
  },
  {
    "title": "Tam, kde štěkají kočky",
    "url": "https://www.kosmas.cz/knihy/568318/tam-kde-stekaji-kocky/",
    "description": "Tam, kde štěkají kočky - Stanislav Beran",
    "authors": [
      "Stanislav Beran"
    ],
    "date": "2026-04-27T07:08:12.900650+00:00"
  },
  {
    "title": "Republika zlodějů",
    "url": "https://www.kosmas.cz/knihy/568324/republika-zlodeju/",
    "description": "Republika zlodějů - Scott Lynch",
    "authors": [
      "Scott Lynch"
    ],
    "date": "2026-04-27T07:08:11.900650+00:00"
  },
  {
    "title": "Taste - Chuť mého života",
    "url": "https://www.kosmas.cz/knihy/567235/taste-chut-meho-zivota/",
    "description": "Taste - Chuť mého života - Stanley Tucci",
    "authors": [
      "Stanley Tucci"
    ],
    "date": "2026-04-27T07:08:10.900650+00:00"
  },
  {
    "title": "Nevěřím v astrologii",
    "url": "https://www.kosmas.cz/knihy/568326/neverim-v-astrologii/",
    "description": "Nevěřím v astrologii - Debra Silverman",
    "authors": [
      "Debra Silverman"
    ],
    "date": "2026-04-27T07:08:09.900650+00:00"
  },
  {
    "title": "Sladký příběh",
    "url": "https://www.kosmas.cz/knihy/568190/sladky-pribeh/",
    "description": "Sladký příběh - Carlton Mellick III",
    "authors": [
      "Carlton Mellick III"
    ],
    "date": "2026-04-26T06:49:20.731634+00:00"
  },
  {
    "title": "Sběratelství: status",
    "url": "https://www.kosmas.cz/knihy/568200/sberatelstvi-status/",
    "description": "Sběratelství: status - Barbora Hájková",
    "authors": [
      "Barbora Hájková"
    ],
    "date": "2026-04-26T06:49:19.731634+00:00"
  },
  {
    "title": "Krvestín",
    "url": "https://www.kosmas.cz/knihy/568328/krvestin/",
    "description": "Krvestín - Jana Karhanová",
    "authors": [
      "Jana Karhanová"
    ],
    "date": "2026-04-26T06:49:17.731634+00:00"
  },
  {
    "title": "Pouto přísahy",
    "url": "https://www.kosmas.cz/knihy/566156/pouto-prisahy/",
    "description": "Pouto přísahy - Tracy Deonn",
    "authors": [
      "Tracy Deonn"
    ],
    "date": "2026-04-26T06:49:16.731634+00:00"
  },
  {
    "title": "Pozemské rozkoše",
    "url": "https://www.kosmas.cz/knihy/566154/pozemske-rozkose/",
    "description": "Pozemské rozkoše - Goldy Moldavsky",
    "authors": [
      "Goldy Moldavsky"
    ],
    "date": "2026-04-26T06:49:15.731634+00:00"
  },
  {
    "title": "Nesmrtelné následky",
    "url": "https://www.kosmas.cz/knihy/568333/nesmrtelne-nasledky/",
    "description": "Nesmrtelné následky - I. V. Marie",
    "authors": [
      "I. V. Marie"
    ],
    "date": "2026-04-26T06:49:14.731634+00:00"
  },
  {
    "title": "Vděk",
    "url": "https://www.kosmas.cz/knihy/568334/vdek/",
    "description": "Vděk - Tracy Wolffová",
    "authors": [
      "Tracy Wolffová"
    ],
    "date": "2026-04-26T06:49:13.731634+00:00"
  },
  {
    "title": "Ela v zemi medvědů",
    "url": "https://www.kosmas.cz/knihy/568335/ela-v-zemi-medvedu/",
    "description": "Ela v zemi medvědů - Michaela Fišarová",
    "authors": [
      "Michaela Fišarová"
    ],
    "date": "2026-04-26T06:49:12.731634+00:00"
  },
  {
    "title": "Mezi nebem a zemí",
    "url": "https://www.kosmas.cz/knihy/568336/mezi-nebem-a-zemi/",
    "description": "Mezi nebem a zemí - Mariana Zapata",
    "authors": [
      "Mariana Zapata"
    ],
    "date": "2026-04-26T06:49:10.731634+00:00"
  },
  {
    "title": "Lesní víla Modlinka",
    "url": "https://www.kosmas.cz/knihy/568343/lesni-vila-modlinka/",
    "description": "Lesní víla Modlinka - Dominika Mecová",
    "authors": [
      "Dominika Mecová"
    ],
    "date": "2026-04-26T06:49:09.731634+00:00"
  },
  {
    "title": "Aréna!",
    "url": "https://www.kosmas.cz/knihy/568348/arena/",
    "description": "Aréna! - Miroslav Beinhauer, Marek Dohnal, Tomáš Šiřina",
    "authors": [
      "Miroslav Beinhauer",
      "Marek Dohnal",
      "Tomáš Šiřina"
    ],
    "date": "2026-04-26T06:49:08.731634+00:00"
  },
  {
    "title": "Valkýry",
    "url": "https://www.kosmas.cz/knihy/512610/valkyry/",
    "description": "Valkýry - Paulo Coelho",
    "authors": [
      "Paulo Coelho"
    ],
    "date": "2026-04-25T06:41:05.432919+00:00"
  },
  {
    "title": "Líbánky v Římě",
    "url": "https://www.kosmas.cz/knihy/567408/libanky-v-rime/",
    "description": "Líbánky v Římě - Irena Kellerová",
    "authors": [
      "Irena Kellerová"
    ],
    "date": "2026-04-25T06:41:04.432919+00:00"
  },
  {
    "title": "Háčkované hračky – želva",
    "url": "https://www.kosmas.cz/knihy/567792/hackovane-hracky-zelva/",
    "description": "Háčkované hračky – želva - kol.",
    "authors": [
      "kol."
    ],
    "date": "2026-04-25T06:41:02.432919+00:00"
  },
  {
    "title": "300 sudoku pro mistry",
    "url": "https://www.kosmas.cz/knihy/567794/300-sudoku-pro-mistry/",
    "description": "300 sudoku pro mistry",
    "authors": [],
    "date": "2026-04-25T06:41:01.432919+00:00"
  },
  {
    "title": "Nálepka nemocná holka",
    "url": "https://www.kosmas.cz/knihy/567811/nalepka-nemocna-holka/",
    "description": "Nálepka nemocná holka - Iva Justychová, Tereza Moravcová",
    "authors": [
      "Iva Justychová",
      "Tereza Moravcová"
    ],
    "date": "2026-04-25T06:41:00.432919+00:00"
  },
  {
    "title": "Marathón",
    "url": "https://www.kosmas.cz/knihy/567841/marathon/",
    "description": "Marathón - Olympic",
    "authors": [
      "Olympic"
    ],
    "date": "2026-04-25T06:40:59.432919+00:00"
  },
  {
    "title": "To nejlepší se Spejblem a Hurvínkem",
    "url": "https://www.kosmas.cz/knihy/567842/to-nejlepsi-se-spejblem-a-hurvinkem/",
    "description": "To nejlepší se Spejblem a Hurvínkem",
    "authors": [],
    "date": "2026-04-25T06:40:58.432919+00:00"
  },
  {
    "title": "Gachiakuta 5",
    "url": "https://www.kosmas.cz/knihy/567873/gachiakuta-5/",
    "description": "Gachiakuta 5 - Kei Urana",
    "authors": [
      "Kei Urana"
    ],
    "date": "2026-04-25T06:40:57.432919+00:00"
  },
  {
    "title": "World of Warcraft – Dědictví stínů 2: Nexus",
    "url": "https://www.kosmas.cz/knihy/567875/world-of-warcraft-dedictvi-stinu-2-nexus/",
    "description": "World of Warcraft – Dědictví stínů 2: Nexus - Richard A. Knaak",
    "authors": [
      "Richard A. Knaak"
    ],
    "date": "2026-04-25T06:40:56.432919+00:00"
  },
  {
    "title": "Teenage Mutant Ninja Turtles 2: New York versus Želvy",
    "url": "https://www.kosmas.cz/knihy/567876/teenage-mutant-ninja-turtles-2-new-york-versus-zelvy/",
    "description": "Teenage Mutant Ninja Turtles 2: New York versus Želvy - Jason Aaron",
    "authors": [
      "Jason Aaron"
    ],
    "date": "2026-04-25T06:40:55.432919+00:00"
  },
  {
    "title": "Zabijáci démonů ve škole 1: Pozdní příchody přísně zakázány",
    "url": "https://www.kosmas.cz/knihy/567880/zabijaci-demonu-ve-skole-1-pozdni-prichody-prisne-zakazany/",
    "description": "Zabijáci démonů ve škole 1: Pozdní příchody přísně zakázány - Nacuki Hokami",
    "authors": [
      "Nacuki Hokami"
    ],
    "date": "2026-04-25T06:40:54.432919+00:00"
  },
  {
    "title": "Jujutsu Kaisen - Prokleté války 18: Horečka",
    "url": "https://www.kosmas.cz/knihy/567881/jujutsu-kaisen-proklete-valky-18-horecka/",
    "description": "Jujutsu Kaisen - Prokleté války 18: Horečka - Gege Akutami",
    "authors": [
      "Gege Akutami"
    ],
    "date": "2026-04-25T06:40:53.432919+00:00"
  },
  {
    "title": "Vraždy v Dekagonu 5",
    "url": "https://www.kosmas.cz/knihy/567888/vrazdy-v-dekagonu-5/",
    "description": "Vraždy v Dekagonu 5 - Jukito Ajacudži",
    "authors": [
      "Jukito Ajacudži"
    ],
    "date": "2026-04-25T06:40:52.432919+00:00"
  },
  {
    "title": "České pohádky - Boženy Němcové (česko-ukrajinské)",
    "url": "https://www.kosmas.cz/knihy/567973/ceske-pohadky-bozeny-nemcove-cesko-ukrajinske/",
    "description": "České pohádky - Boženy Němcové (česko-ukrajinské) - Božena Němcová",
    "authors": [
      "Božena Němcová"
    ],
    "date": "2026-04-25T06:40:51.432919+00:00"
  },
  {
    "title": "Základy arabštiny a arabská četba se zaměřením na náboženství a kulturu",
    "url": "https://www.kosmas.cz/knihy/568051/zaklady-arabstiny-a-arabska-cetba-se-zamerenim-na-nabozenstvi-a-kulturu/",
    "description": "Základy arabštiny a arabská četba se zaměřením na náboženství a kulturu - Mlada Mikulicová",
    "authors": [
      "Mlada Mikulicová"
    ],
    "date": "2026-04-25T06:40:50.432919+00:00"
  },
  {
    "title": "Adresát Bohuslav Havránek",
    "url": "https://www.kosmas.cz/knihy/568052/adresat-bohuslav-havranek/",
    "description": "Adresát Bohuslav Havránek - Marie Havránková, Vladimír Petkevič",
    "authors": [
      "Marie Havránková",
      "Vladimír Petkevič"
    ],
    "date": "2026-04-25T06:40:49.432919+00:00"
  },
  {
    "title": "Oncology",
    "url": "https://www.kosmas.cz/knihy/568053/oncology/",
    "description": "Oncology - Renata Soumarová",
    "authors": [
      "Renata Soumarová"
    ],
    "date": "2026-04-25T06:40:48.432919+00:00"
  },
  {
    "title": "Doporučený postup diagnostiky a léčby těžkého astmatu",
    "url": "https://www.kosmas.cz/knihy/568139/doporuceny-postup-diagnostiky-a-lecby-tezkeho-astmatu/",
    "description": "Doporučený postup diagnostiky a léčby těžkého astmatu - Irena Krčmová, Vratislav Sedlák, Milan Teřl, kol.",
    "authors": [
      "Irena Krčmová",
      "Vratislav Sedlák",
      "Milan Teřl",
      "kol."
    ],
    "date": "2026-04-25T06:40:47.432919+00:00"
  },
  {
    "title": "Polyvagální cvičení",
    "url": "https://www.kosmas.cz/knihy/568162/polyvagalni-cviceni/",
    "description": "Polyvagální cvičení - Deb Dana",
    "authors": [
      "Deb Dana"
    ],
    "date": "2026-04-25T06:40:46.432919+00:00"
  },
  {
    "title": "Yamal",
    "url": "https://www.kosmas.cz/knihy/567699/yamal/",
    "description": "Yamal - Dan Green, Dan Green, Simon Mugford",
    "authors": [
      "Dan Green",
      "Dan Green",
      "Simon Mugford"
    ],
    "date": "2026-04-24T06:52:03.958492+00:00"
  },
  {
    "title": "Kočka",
    "url": "https://www.kosmas.cz/knihy/568175/kocka/",
    "description": "Kočka",
    "authors": [],
    "date": "2026-04-24T06:52:02.958492+00:00"
  },
  {
    "title": "10 bylinkových pohádek",
    "url": "https://www.kosmas.cz/knihy/568207/10-bylinkovych-pohadek/",
    "description": "10 bylinkových pohádek - Lenka Jakešová",
    "authors": [
      "Lenka Jakešová"
    ],
    "date": "2026-04-24T06:52:01.958492+00:00"
  },
  {
    "title": "Pozorování ptáků",
    "url": "https://www.kosmas.cz/knihy/560561/pozorovani-ptaku/",
    "description": "Pozorování ptáků - Chris Packham",
    "authors": [
      "Chris Packham"
    ],
    "date": "2026-04-24T06:52:00.958492+00:00"
  },
  {
    "title": "Zálesák",
    "url": "https://www.kosmas.cz/knihy/568101/zalesak/",
    "description": "Zálesák - Zane Grey",
    "authors": [
      "Zane Grey"
    ],
    "date": "2026-04-24T06:51:59.958492+00:00"
  },
  {
    "title": "Jedno temné okno",
    "url": "https://www.kosmas.cz/knihy/568218/jedno-temne-okno/",
    "description": "Jedno temné okno - Rachel Gilling",
    "authors": [
      "Rachel Gilling"
    ],
    "date": "2026-04-24T06:51:58.958492+00:00"
  },
  {
    "title": "Vor v zakone",
    "url": "https://www.kosmas.cz/knihy/568250/vor-v-zakone/",
    "description": "Vor v zakone - Vítězslav Jareš",
    "authors": [
      "Vítězslav Jareš"
    ],
    "date": "2026-04-24T06:51:57.958492+00:00"
  },
  {
    "title": "Tajemno napříč stoletími",
    "url": "https://www.kosmas.cz/knihy/568253/tajemno-napric-stoletimi/",
    "description": "Tajemno napříč stoletími - Zuzana Muchová-Daxnerová",
    "authors": [
      "Zuzana Muchová-Daxnerová"
    ],
    "date": "2026-04-24T06:51:56.958492+00:00"
  },
  {
    "title": "Smrt je vrahům v patách / Když zákon nestačí",
    "url": "https://www.kosmas.cz/knihy/568256/smrt-je-vrahum-v-patach-kdyz-zakon-nestaci/",
    "description": "Smrt je vrahům v patách / Když zákon nestačí - Jiljí Kocian",
    "authors": [
      "Jiljí Kocian"
    ],
    "date": "2026-04-24T06:51:55.958492+00:00"
  },
  {
    "title": "Komplikace",
    "url": "https://www.kosmas.cz/knihy/568270/komplikace/",
    "description": "Komplikace - Danielle Steel",
    "authors": [
      "Danielle Steel"
    ],
    "date": "2026-04-24T06:51:53.958492+00:00"
  },
  {
    "title": "Rozkvetlá",
    "url": "https://www.kosmas.cz/knihy/568281/rozkvetla/",
    "description": "Rozkvetlá - Renáta Krejčí",
    "authors": [
      "Renáta Krejčí"
    ],
    "date": "2026-04-24T06:51:52.958492+00:00"
  },
  {
    "title": "Vražedné peníze",
    "url": "https://www.kosmas.cz/knihy/564789/vrazedne-penize/",
    "description": "Vražedné peníze - Cara Hunterová",
    "authors": [
      "Cara Hunterová"
    ],
    "date": "2026-04-24T06:51:51.958492+00:00"
  },
  {
    "title": "Ohňostroj mezi námi",
    "url": "https://www.kosmas.cz/knihy/565423/ohnostroj-mezi-nami/",
    "description": "Ohňostroj mezi námi - Kyra Groh",
    "authors": [
      "Kyra Groh"
    ],
    "date": "2026-04-24T06:51:50.958492+00:00"
  },
  {
    "title": "Týden v Nejistotě",
    "url": "https://www.kosmas.cz/knihy/568290/tyden-v-nejistote/",
    "description": "Týden v Nejistotě - Iva Sušická",
    "authors": [
      "Iva Sušická"
    ],
    "date": "2026-04-24T06:51:49.958492+00:00"
  },
  {
    "title": "Hovořil se zvěří, ptáky a rybami",
    "url": "https://www.kosmas.cz/knihy/568291/hovoril-se-zveri-ptaky-a-rybami/",
    "description": "Hovořil se zvěří, ptáky a rybami - Konrad Lorenz",
    "authors": [
      "Konrad Lorenz"
    ],
    "date": "2026-04-24T06:51:48.958492+00:00"
  },
  {
    "title": "Věř si",
    "url": "https://www.kosmas.cz/knihy/564004/ver-si/",
    "description": "Věř si - Tama Kivesová",
    "authors": [
      "Tama Kivesová"
    ],
    "date": "2026-04-24T06:51:47.958492+00:00"
  },
  {
    "title": "Edvard Beneš: Paměti - kompletní vydání",
    "url": "https://www.kosmas.cz/knihy/568297/edvard-benes-pameti-kompletni-vydani/",
    "description": "Edvard Beneš: Paměti - kompletní vydání - Edvard Beneš",
    "authors": [
      "Edvard Beneš"
    ],
    "date": "2026-04-24T06:51:46.958492+00:00"
  },
  {
    "title": "Nejsladší píseň",
    "url": "https://www.kosmas.cz/knihy/567610/nejsladsi-pisen/",
    "description": "Nejsladší píseň - Richard Wurmbrand",
    "authors": [
      "Richard Wurmbrand"
    ],
    "date": "2026-04-24T06:51:45.958492+00:00"
  },
  {
    "title": "Duch Pankráce",
    "url": "https://www.kosmas.cz/knihy/567611/duch-pankrace/",
    "description": "Duch Pankráce - Petra Klabouchová",
    "authors": [
      "Petra Klabouchová"
    ],
    "date": "2026-04-24T06:51:44.958492+00:00"
  },
  {
    "title": "Skrytá říše",
    "url": "https://www.kosmas.cz/knihy/568070/skryta-rise/",
    "description": "Skrytá říše - Holly Renee",
    "authors": [
      "Holly Renee"
    ],
    "date": "2026-04-23T06:51:08.996854+00:00"
  },
  {
    "title": "Architekt hněvu",
    "url": "https://www.kosmas.cz/knihy/568068/architekt-hnevu/",
    "description": "Architekt hněvu - Ondřej Blaho",
    "authors": [
      "Ondřej Blaho"
    ],
    "date": "2026-04-23T06:51:07.996854+00:00"
  },
  {
    "title": "Nemravné sliby",
    "url": "https://www.kosmas.cz/knihy/568112/nemravne-sliby/",
    "description": "Nemravné sliby - Alessandra Torre",
    "authors": [
      "Alessandra Torre"
    ],
    "date": "2026-04-23T06:51:06.996854+00:00"
  },
  {
    "title": "Muž z Brna na Onom Světě",
    "url": "https://www.kosmas.cz/knihy/565422/muz-z-brna-na-onom-svete/",
    "description": "Muž z Brna na Onom Světě - Petra Klabouchová",
    "authors": [
      "Petra Klabouchová"
    ],
    "date": "2026-04-23T06:51:05.996854+00:00"
  },
  {
    "title": "Zlá babička",
    "url": "https://www.kosmas.cz/knihy/568209/zla-babicka/",
    "description": "Zlá babička - Ditta Kůtová",
    "authors": [
      "Ditta Kůtová"
    ],
    "date": "2026-04-23T06:51:04.996854+00:00"
  },
  {
    "title": "Jak mluvit s dětmi o penězích",
    "url": "https://www.kosmas.cz/knihy/566784/jak-mluvit-s-detmi-o-penezich/",
    "description": "Jak mluvit s dětmi o penězích - Martina Burešová",
    "authors": [
      "Martina Burešová"
    ],
    "date": "2026-04-23T06:51:03.996854+00:00"
  },
  {
    "title": "Z Prahy do Jeruzaléma a zpět",
    "url": "https://www.kosmas.cz/knihy/567289/z-prahy-do-jeruzalema-a-zpet/",
    "description": "Z Prahy do Jeruzaléma a zpět - Tomáš Kulka",
    "authors": [
      "Tomáš Kulka"
    ],
    "date": "2026-04-23T06:51:02.996854+00:00"
  },
  {
    "title": "Život ve 280 znacích",
    "url": "https://www.kosmas.cz/knihy/568135/zivot-ve-280-znacich/",
    "description": "Život ve 280 znacích - Alex Nesien",
    "authors": [
      "Alex Nesien"
    ],
    "date": "2026-04-23T06:51:01.996854+00:00"
  },
  {
    "title": "Temná řeka",
    "url": "https://www.kosmas.cz/knihy/567513/temna-reka/",
    "description": "Temná řeka - Ping Lu",
    "authors": [
      "Ping Lu"
    ],
    "date": "2026-04-23T06:51:00.996854+00:00"
  }
]